powerBIParser/__init__.py
powerBIParser/field.py
powerBIParser/fieldInterface.py
powerBIParser/measure.py
powerBIParser/pbiDatasetParser.py
powerBIParser/pbiItemParser.py
powerBIParser/pbiReportParser.py
powerBIParser/relationship.py
powerBIParser/section.py
powerBIParser/table.py
powerbi_parser-1.0.7.dist-info/LICENSE
powerbi_parser-1.0.7.dist-info/METADATA
powerbi_parser-1.0.7.dist-info/WHEEL
powerbi_parser-1.0.7.dist-info/top_level.txt
powerbi_parser-1.0.7.dist-info/RECORD
