Metadata-Version: 2.1
Name: powerbi-parser
Version: 1.0.7
Summary: Parser Power BI files to browse assets
Home-page: https://github.com/Resousse/python-powerbi-parser
Author: Resousse
Author-email: resousegit@gmail.com
License: Apache 2.0
License-File: LICENSE
